DAStk/__init__.py
DAStk/barcode_plot.py
DAStk/differential_md_score.py
DAStk/ma_plot.py
DAStk/process_atac.py
DAStk/tf_intersect.py
DAStk/tf_result_explanations.py
DAStk/public_knowledge/HOCOMOCOv11_to_uniprot.txt
DAStk/public_knowledge/all_labels.tsv
DAStk/public_knowledge/human_TFs_to_uniprot.txt
DAStk/public_knowledge/prot_reactome_interactions.pkl
DAStk-1.0.0.dist-info/LICENSE
DAStk-1.0.0.dist-info/METADATA
DAStk-1.0.0.dist-info/WHEEL
DAStk-1.0.0.dist-info/entry_points.txt
DAStk-1.0.0.dist-info/top_level.txt
DAStk-1.0.0.dist-info/RECORD
