Metadata-Version: 2.1
Name: DAStk
Version: 1.0.0
Summary: Differential ATAC-seq toolkit
Home-page: https://github.com/Dowell-Lab/DAStk
Author: Ignacio Tripodi
Author-email: ignacio.tripodi@colorado.edu
License: BSD
Project-URL: Source, https://github.com/Dowell-Lab/DAStk
Project-URL: Human Motif Sites (GRCh38), http://dowell.colorado.edu/pubs/DAStk/motifs/HOCOMOCO_v11_p1e-6_grch38.tar.gz
Project-URL: Human Motif Sites (hg19), http://dowell.colorado.edu/pubs/DAStk/motifs/HOCOMOCO_v11_p1e-6_hg19.tar.gz
Project-URL: Bug Reports, https://github.com/Dowell-Lab/DAStk/issues
Project-URL: Mouse Motif Sites (mm10), http://dowell.colorado.edu/pubs/DAStk/motifs/HOCOMOCO_v11_p1e-6_mm10.tar.gz
Keywords: bioinformatics genomics chromatin ATAC-seq motif transcription_factor TF
Platform: UNKNOWN
Classifier: Development Status :: 4 - Beta
Classifier: Environment :: Console
Classifier: Intended Audience :: Developers
Classifier: Intended Audience :: Science/Research
Classifier: Topic :: Scientific/Engineering :: Bio-Informatics
Classifier: License :: OSI Approved :: BSD License
Classifier: Programming Language :: Python :: 2
Classifier: Programming Language :: Python :: 3
Requires-Python: >=2.7
Requires-Dist: argparse
Requires-Dist: datetime
Requires-Dist: numpy
Requires-Dist: matplotlib
Requires-Dist: adjustText
Requires-Dist: scipy
Requires-Dist: pandas
Requires-Dist: pybedtools
Requires-Dist: futures
Requires-Dist: scikit-learn
Requires-Dist: networkx (>=2)
Requires-Dist: upsetplot
